shopify_spy/__init__.py
shopify_spy/cli.py
shopify_spy/config.py
shopify_spy/settings.py
shopify_spy/utils.py
shopify_spy/spiders/__init__.py
shopify_spy/spiders/shopify.py
shopify_spy-0.1.0.dist-info/METADATA
shopify_spy-0.1.0.dist-info/WHEEL
shopify_spy-0.1.0.dist-info/entry_points.txt
shopify_spy-0.1.0.dist-info/licenses/LICENSE
shopify_spy-0.1.0.dist-info/RECORD
