Metadata-Version: 2.4
Name: shopify-spy
Version: 0.1.0
Summary: Simple CLI to scrape product data, images, and collections from Shopify stores
Project-URL: Homepage, https://github.com/ndgigliotti/shopify-spy
Project-URL: Repository, https://github.com/ndgigliotti/shopify-spy
Project-URL: Bug Tracker, https://github.com/ndgigliotti/shopify-spy/issues
Author-email: Nicholas Gigliotti <ndgigliotti@gmail.com>
License-Expression: MIT
License-File: LICENSE
Keywords: ecommerce,product-data,scraper,scrapy,shopify,spider,web-scraping
Classifier: Development Status :: 4 - Beta
Classifier: Environment :: Console
Classifier: Framework :: Scrapy
Classifier: Intended Audience :: Developers
Classifier: License :: OSI Approved :: MIT License
Classifier: Operating System :: OS Independent
Classifier: Programming Language :: Python :: 3
Classifier: Programming Language :: Python :: 3.10
Classifier: Programming Language :: Python :: 3.11
Classifier: Programming Language :: Python :: 3.12
Classifier: Programming Language :: Python :: 3.13
Classifier: Topic :: Internet :: WWW/HTTP :: Indexing/Search
Requires-Python: >=3.10
Requires-Dist: pillow>=10.0
Requires-Dist: pydantic>=2.0
Requires-Dist: pyyaml>=6.0
Requires-Dist: rich>=13.0
Requires-Dist: scrapy>=2.11
Requires-Dist: typer>=0.15
Provides-Extra: dev
Requires-Dist: pre-commit>=4.0; extra == 'dev'
Requires-Dist: pytest>=8.0; extra == 'dev'
Requires-Dist: ruff>=0.9; extra == 'dev'
